{
    "en": {
        "group_alertLayout": "layout",
        "group_autoCompleteListLayout": "menu layout",
        "group_barColors": "bar chart colors:",
        "group_barLayout": "bar chart layout:",
        "group_barValuesLayout": "bar chart values layout:",
        "group_buttonLayout": "Button Layout",
        "group_buttonOids": "Object Id",
        "group_calendarButtonsLayout": "calendar buttons layout",
        "group_calendarCustomFormats": "custom date formats",
        "group_calendarEventLayout": "appointment layout",
        "group_calendarHeaderLayout": "heading layout",
        "group_calendarLayout": "layout",
        "group_calendarTimeAxisLayout": "time axis layout",
        "group_calendarWeekNumbersLayout": "calendar weeks layout",
        "group_changeEffect": "value change effect",
        "group_chartLayout": "chart layout:",
        "group_color": "colors",
        "group_columnLayout": "column layout",
        "group_common": "Common",
        "group_title": "title",
        "group_text": "text",
        "group_controlCard": "card action",
        "group_formatLinked": "linked value",
        "group_layoutStriped": "striped",
        "group_listHeader": "list header",
        "group_commonYAxis": "common y-axis",
        "group_controlLayout": "control layout",
        "group_counter": "counter layout",
        "group_drawerColors": "navigation bar colors",
        "group_drawerDivider": "dividers for navigation bar",
        "group_drawerHeaders": "headers for navigation bar",
        "group_drawerIcons": "icons for navigation bar",
        "group_drawerItems": "item of navigation bar",
        "group_drawerItemsData": "data of navigation bar",
        "group_drawerLabels": "label for navigation bar",
        "group_drawerLayout": "navigation bar layout",
        "group_drawerSubItemsColors": "navigation bar: sub menu colors",
        "group_drawerSubItemsLayout": "navigation bar: sub menu layout",
        "group_extraMyset": "extraMyset",
        "group_font": "fonts",
        "group_fontSize": "font sizes",
        "group_formatBoolean": "boolean formatting",
        "group_formatNumber": "number formatting",
        "group_handySettings": "mobile phone settings",
        "group_icon": "icon",
        "group_iconListHeader": "headline",
        "group_icons": "icons",
        "group_iFrame": "iFrame settings",
        "group_image": "image",
        "group_inputAppendix": "appendixs of the input",
        "group_inputLabel": "label of input ",
        "group_inputLayout": "layout input ",
        "group_inputSubText": "sub text of input",
        "group_label": "labeling",
        "group_labels": "labels",
        "group_labelValuesAppend": "value text appendix",
        "group_layout": "layout",
        "group_layoutDialog": "Dialog Layout",
        "group_layoutdialogCloseButton": "layout of dialog footer buttons",
        "group_layoutForData": "layout for data",
        "group_layoutTitle": "title layout",
        "group_legendLayout": "legend layout:",
        "group_lineLayout": "line layout",
        "group_lineValuesLayout": "layout of line chart values",
        "group_listData": "data of menu",
        "group_listItemCardBackground": "card background",
        "group_listItemData": "data of list",
        "group_listItemLayout": "layout of list item",
        "group_listLayout": "layout of list",
        "group_lock": "Locking",
        "group_theme": "Theme",
        "group_menuColors": "menu colors",
        "group_menuItems": "menu item",
        "group_oids": "dataset",
        "group_pieColors": "pie chart colors:",
        "group_pieLayout": "pie chart layout:",
        "group_pieValuesLayout": "pie chart values layout:",
        "group_rows": "layout of list item",
        "group_selectColor": "colors",
        "group_selectListLayout": "menu layout",
        "group_submenus": "sub menus",
        "group_tableLayout": "layout",
        "group_tabletSettings": "tablet settings",
        "group_thumbLabelLayout": "layout of the controller label",
        "group_tickLayout": "steps Layout",
        "group_tooltipLayout": "tooltip layout:",
        "group_topAppBarLayout": "top app bar layout",
        "group_valueTextColors": "value text colors",
        "group_View": "View",
        "group_viewsInColumn": "views in column",
        "group_xAxisLayout": "x axis layout",
        "group_yAxisLayout": "y axis layout",
        "group_yAxisLayoutForData": "y-axis layout for data"
    },
    "de": {
        "group_alertLayout": "Layout",
        "group_autoCompleteListLayout": "Menü-Layout",
        "group_barColors": "Balkendiagrammfarben:",
        "group_barLayout": "Balkendiagramm Layout:",
        "group_barValuesLayout": "Balkendiagrammwerte Layout:",
        "group_buttonLayout": "Button Layout",
        "group_buttonOids": "Objekt Id",
        "group_calendarButtonsLayout": "Layout der Kalendertasten",
        "group_calendarCustomFormats": "benutzerdefinierte Datumsformate",
        "group_calendarEventLayout": "Terminlayout",
        "group_calendarHeaderLayout": "Überschriftenlayout",
        "group_calendarLayout": "Layout",
        "group_calendarTimeAxisLayout": "Zeitachsenlayout",
        "group_calendarWeekNumbersLayout": "Kalenderwochen Layout",
        "group_changeEffect": "Wertänderungseffekt",
        "group_chartLayout": "Diagramm Layout:",
        "group_color": "Farben",
        "group_columnLayout": "Spaltenlayout",
        "group_common": "Allgemein",
        "group_title": "Titel",
        "group_text": "Text",
        "group_controlCard": "Kartenaktion",
        "group_formatLinked": "Verknüpfter Wert",
        "group_layoutStriped": "Streifen",
        "group_listHeader": "Listenkopf",
        "group_commonYAxis": "gemeinsame y-Achse",
        "group_controlLayout": "Steuerungslayout",
        "group_counter": "Zählerlayout",
        "group_drawerColors": "Navigationsleiste: Farben",
        "group_drawerDivider": "Navigationsleiste: Trennlinien",
        "group_drawerHeaders": "Navigationsleiste: Überschriften",
        "group_drawerIcons": "Navigationsleiste: Bilder",
        "group_drawerItems": "Navigationsleiste: Element",
        "group_drawerItemsData": "Navigationsleiste: Daten",
        "group_drawerLabels": "Navigationsleiste: Beschriftungen",
        "group_drawerLayout": "Navigationsleiste: Layout",
        "group_drawerSubItemsColors": "Navigationsleiste: Untermenüfarben",
        "group_drawerSubItemsLayout": "Navigationsleiste: Untermenü-Layout",
        "group_extraMyset": "extraMyset",
        "group_font": "Schriftarten",
        "group_fontSize": "Schriftgrößen",
        "group_formatBoolean": "Logikwert Formatierung",
        "group_formatNumber": "Zahlenformatierung",
        "group_handySettings": "Handy Einstellungen",
        "group_icon": "Symbol",
        "group_iconListHeader": "Überschrift",
        "group_icons": "Symbole",
        "group_iFrame": "iFrame Einstellungen",
        "group_image": "Bild",
        "group_inputAppendix": "Anhänge der Eingabe",
        "group_inputLabel": "Beschriftung der Eingabe",
        "group_inputLayout": "Layout Eingabe",
        "group_inputSubText": "Untertext der Eingabe",
        "group_label": "Beschriftung",
        "group_labels": "Beschriftungen",
        "group_labelValuesAppend": "Wert Textanhang",
        "group_layout": "Layout",
        "group_layoutDialog": "Layout Dialog",
        "group_layoutdialogCloseButton": "Layout der Schaltflächen in der Dialogfußzeile",
        "group_layoutForData": "Layout für Datensatz",
        "group_layoutTitle": "Layout Kopfzeile",
        "group_legendLayout": "Legenden Layout:",
        "group_lineLayout": "Linien Layout",
        "group_lineValuesLayout": "Layout der Liniendiagrammwerte",
        "group_listData": "Daten des Menüs",
        "group_listItemCardBackground": "Card Hintergrund",
        "group_listItemData": "Daten der Liste",
        "group_listItemLayout": "Layout des Listenelements",
        "group_listLayout": "Layout der Liste",
        "group_lock": "Verriegeln",
        "group_theme": "Thema",
        "group_menuColors": "Menüfarben",
        "group_menuItems": "Menüpunkt",
        "group_oids": "Datensatz",
        "group_pieColors": "Kreisdiagrammfarben:",
        "group_pieLayout": "Kreisdiagramm Layout:",
        "group_pieValuesLayout": "Kreisdiagrammwerte Layout:",
        "group_rows": "Layout des Listenelements",
        "group_selectColor": "Farben",
        "group_selectListLayout": "Menü-Layout",
        "group_submenus": "Untermenüs",
        "group_tableLayout": "Layout",
        "group_tabletSettings": "Tablet Einstellungen",
        "group_thumbLabelLayout": "Layout des Regler-Label",
        "group_tickLayout": "Schritte Layout",
        "group_tooltipLayout": "Tooltip Layout:",
        "group_topAppBarLayout": "Top App Bar Layout",
        "group_valueTextColors": "Wert Textfarben",
        "group_View": "View",
        "group_viewsInColumn": "Ansichten in der Spalte",
        "group_xAxisLayout": "x-Achsen Layout",
        "group_yAxisLayout": "y-Achsen Layout",
        "group_yAxisLayoutForData": "y-Achsen-Layout für Datensatz"
    },
    "es": {
        "group_alertLayout": "diseño",
        "group_autoCompleteListLayout": "diseño del menú",
        "group_barColors": "colores del gráfico de barras:",
        "group_barLayout": "diseño del gráfico de barras:",
        "group_barValuesLayout": "diseño de valores del gráfico de barras:",
        "group_buttonLayout": "Diseño de botones",
        "group_buttonOids": "ID de objeto",
        "group_calendarButtonsLayout": "diseño de botones de calendario",
        "group_calendarCustomFormats": "formatos de fecha personalizados",
        "group_calendarEventLayout": "diseño de cita",
        "group_calendarHeaderLayout": "diseño de rumbo",
        "group_calendarLayout": "diseño",
        "group_calendarTimeAxisLayout": "diseño del eje de tiempo",
        "group_calendarWeekNumbersLayout": "diseño de semanas de calendario",
        "group_changeEffect": "efecto de cambio de valor",
        "group_chartLayout": "diseño del gráfico:",
        "group_color": "colores",
        "group_columnLayout": "diseño de columna",
        "group_common": "Common",
        "group_title": "título",
        "group_text": "texto",
        "group_controlCard": "acción de la tarjeta",
        "group_formatLinked": "valor vinculado",
        "group_layoutStriped": "rayado",
        "group_listHeader": "encabezado de lista",
        "group_commonYAxis": "eje y común",
        "group_controlLayout": "diseño de control",
        "group_counter": "diseño de mostrador",
        "group_drawerColors": "colores de la barra de navegación",
        "group_drawerDivider": "divisores para barra de navegación",
        "group_drawerHeaders": "encabezados para barra de navegación",
        "group_drawerIcons": "iconos para barra de navegación",
        "group_drawerItems": "elemento de la barra de navegación",
        "group_drawerItemsData": "datos de la barra de navegación",
        "group_drawerLabels": "etiqueta para barra de navegación",
        "group_drawerLayout": "diseño de la barra de navegación",
        "group_drawerSubItemsColors": "barra de navegación: colores del submenú",
        "group_drawerSubItemsLayout": "barra de navegación: diseño del submenú",
        "group_extraMyset": "extraMyset",
        "group_font": "fuentes",
        "group_fontSize": "tamaños de fuente",
        "group_formatBoolean": "formato booleano",
        "group_formatNumber": "formato de número",
        "group_handySettings": "configuración del teléfono móvil",
        "group_icon": "icono",
        "group_iconListHeader": "Titular",
        "group_icons": "íconos",
        "group_iFrame": "configuración de iFrame",
        "group_image": "imagen",
        "group_inputAppendix": "apéndices de la entrada",
        "group_inputLabel": "etiqueta de entrada",
        "group_inputLayout": "entrada de diseño",
        "group_inputSubText": "sub texto de entrada",
        "group_label": "etiquetado",
        "group_labels": "etiquetas",
        "group_labelValuesAppend": "apéndice de texto de valor",
        "group_layout": "diseño",
        "group_layoutDialog": "Dialog Layout",
        "group_layoutdialogCloseButton": "diseño de los botones de pie de página de diálogo",
        "group_layoutForData": "diseño para datos",
        "group_layoutTitle": "diseño del título",
        "group_legendLayout": "diseño de leyenda:",
        "group_lineLayout": "diseño de línea",
        "group_lineValuesLayout": "diseño de los valores del gráfico de líneas",
        "group_listData": "datos del menú",
        "group_listItemCardBackground": "fondo de la tarjeta",
        "group_listItemData": "datos de la lista",
        "group_listItemLayout": "diseño del elemento de la lista",
        "group_listLayout": "diseño de la lista",
        "group_lock": "Cierre",
        "group_theme": "Tema",
        "group_menuColors": "colores del menú",
        "group_menuItems": "opción del menú",
        "group_oids": "conjunto de datos",
        "group_pieColors": "colores del gráfico circular:",
        "group_pieLayout": "diseño de gráfico circular:",
        "group_pieValuesLayout": "diseño de valores de gráfico circular:",
        "group_rows": "diseño del elemento de la lista",
        "group_selectColor": "colores",
        "group_selectListLayout": "diseño del menú",
        "group_submenus": "submenús",
        "group_tableLayout": "diseño",
        "group_tabletSettings": "configuración de la tableta",
        "group_thumbLabelLayout": "diseño de la etiqueta del controlador",
        "group_tickLayout": "pasos de diseño",
        "group_tooltipLayout": "diseño de información sobre herramientas:",
        "group_topAppBarLayout": "diseño de la barra de la aplicación superior",
        "group_valueTextColors": "colores de texto de valor",
        "group_View": "Ver",
        "group_viewsInColumn": "vistas en columna",
        "group_xAxisLayout": "diseño del eje x",
        "group_yAxisLayout": "diseño del eje y",
        "group_yAxisLayoutForData": "diseño del eje y para datos"
    },
    "fr": {
        "group_alertLayout": "disposition",
        "group_autoCompleteListLayout": "disposition des menus",
        "group_barColors": "couleurs du graphique à barres:",
        "group_barLayout": "Diagramme à barres:",
        "group_barValuesLayout": "Diagramme à barres mise en page:",
        "group_buttonLayout": "Disposition des boutons",
        "group_buttonOids": "Id d'objet",
        "group_calendarButtonsLayout": "disposition des boutons de calendrier",
        "group_calendarCustomFormats": "formats de date personnalisés",
        "group_calendarEventLayout": "disposition des rendez-vous",
        "group_calendarHeaderLayout": "disposition des en-têtes",
        "group_calendarLayout": "disposition",
        "group_calendarTimeAxisLayout": "disposition de l'axe du temps",
        "group_calendarWeekNumbersLayout": "disposition des semaines calendaires",
        "group_changeEffect": "effet de changement de valeur",
        "group_chartLayout": "mise en page graphique:",
        "group_color": "couleurs",
        "group_columnLayout": "disposition des colonnes",
        "group_common": "Common",
        "group_title": "titre",
        "group_text": "texte",
        "group_controlCard": "action de la carte",
        "group_formatLinked": "valeur liée",
        "group_layoutStriped": "rayé",
        "group_listHeader": "en-tête de liste",
        "group_commonYAxis": "axe y commun",
        "group_controlLayout": "disposition de contrôle",
        "group_counter": "disposition du comptoir",
        "group_drawerColors": "couleurs de la barre de navigation",
        "group_drawerDivider": "séparateurs pour barre de navigation",
        "group_drawerHeaders": "en-têtes pour la barre de navigation",
        "group_drawerIcons": "icônes pour la barre de navigation",
        "group_drawerItems": "élément de la barre de navigation",
        "group_drawerItemsData": "données de la barre de navigation",
        "group_drawerLabels": "étiquette pour la barre de navigation",
        "group_drawerLayout": "disposition de la barre de navigation",
        "group_drawerSubItemsColors": "barre de navigation: couleurs du sous-menu",
        "group_drawerSubItemsLayout": "barre de navigation: disposition du sous-menu",
        "group_extraMyset": "extraMyset",
        "group_font": "polices",
        "group_fontSize": "tailles de police",
        "group_formatBoolean": "formatage booléen",
        "group_formatNumber": "formatage des nombres",
        "group_handySettings": "paramètres de téléphone mobile",
        "group_icon": "icône",
        "group_iconListHeader": "Gros titre",
        "group_icons": "Icônes",
        "group_iFrame": "paramètres iFrame",
        "group_image": "image",
        "group_inputAppendix": "annexes de l'entrée",
        "group_inputLabel": "étiquette d'entrée",
        "group_inputLayout": "entrée de mise en page",
        "group_inputSubText": "sous-texte d'entrée",
        "group_label": "étiquetage",
        "group_labels": "Étiquettes",
        "group_labelValuesAppend": "annexe texte valeur",
        "group_layout": "disposition",
        "group_layoutDialog": "Disposition des dialogues",
        "group_layoutdialogCloseButton": "disposition des boutons de pied de page de la boîte de dialogue",
        "group_layoutForData": "mise en page pour les données",
        "group_layoutTitle": "mise en page du titre",
        "group_legendLayout": "disposition de la légende:",
        "group_lineLayout": "mise en ligne",
        "group_lineValuesLayout": "disposition des valeurs du graphique en courbes",
        "group_listData": "données de menu",
        "group_listItemCardBackground": "fond de carte",
        "group_listItemData": "données de liste",
        "group_listItemLayout": "mise en page de l'élément de liste",
        "group_listLayout": "mise en page de la liste",
        "group_lock": "Verrouillage",
        "group_theme": "Thème",
        "group_menuColors": "couleurs du menu",
        "group_menuItems": "élément du menu",
        "group_oids": "base de données",
        "group_pieColors": "camembert couleurs:",
        "group_pieLayout": "graphique en camembert:",
        "group_pieValuesLayout": "Mise en page des valeurs du graphique à secteurs:",
        "group_rows": "mise en page de l'élément de liste",
        "group_selectColor": "couleurs",
        "group_selectListLayout": "disposition des menus",
        "group_submenus": "sous-menus",
        "group_tableLayout": "disposition",
        "group_tabletSettings": "paramètres de la tablette",
        "group_thumbLabelLayout": "disposition de l'étiquette du contrôleur",
        "group_tickLayout": "mise en page des étapes",
        "group_tooltipLayout": "mise en page info-bulle:",
        "group_topAppBarLayout": "top mise en page de la barre d'application",
        "group_valueTextColors": "Valoriser les couleurs du texte",
        "group_View": "Vue",
        "group_viewsInColumn": "vues en colonne",
        "group_xAxisLayout": "disposition des axes x",
        "group_yAxisLayout": "Disposition en Y",
        "group_yAxisLayoutForData": "disposition en ordonnée pour les données"
    },
    "it": {
        "group_alertLayout": "disposizione",
        "group_autoCompleteListLayout": "layout del menu",
        "group_barColors": "colori del grafico a barre:",
        "group_barLayout": "layout grafico a barre:",
        "group_barValuesLayout": "layout valori grafico a barre:",
        "group_buttonLayout": "Disposizione dei pulsanti",
        "group_buttonOids": "ID oggetto",
        "group_calendarButtonsLayout": "layout pulsanti calendario",
        "group_calendarCustomFormats": "formati di data personalizzati",
        "group_calendarEventLayout": "layout dell'appuntamento",
        "group_calendarHeaderLayout": "layout di intestazione",
        "group_calendarLayout": "disposizione",
        "group_calendarTimeAxisLayout": "layout dell'asse temporale",
        "group_calendarWeekNumbersLayout": "layout di settimane di calendario",
        "group_changeEffect": "effetto di cambio di valore",
        "group_chartLayout": "layout grafico:",
        "group_color": "colori",
        "group_columnLayout": "layout di colonna",
        "group_common": "Common",
        "group_title": "titolo",
        "group_text": "testo",
        "group_controlCard": "azione della scheda",
        "group_formatLinked": "valore collegato",
        "group_layoutStriped": "a righe",
        "group_listHeader": "intestazione elenco",
        "group_commonYAxis": "asse y comune",
        "group_controlLayout": "layout di controllo",
        "group_counter": "contro layout",
        "group_drawerColors": "colori della barra di navigazione",
        "group_drawerDivider": "divisori per barra di navigazione",
        "group_drawerHeaders": "intestazioni per la barra di navigazione",
        "group_drawerIcons": "icone per la barra di navigazione",
        "group_drawerItems": "elemento della barra di navigazione",
        "group_drawerItemsData": "dati della barra di navigazione",
        "group_drawerLabels": "etichetta per barra di navigazione",
        "group_drawerLayout": "layout della barra di navigazione",
        "group_drawerSubItemsColors": "barra di navigazione: colori del sottomenu",
        "group_drawerSubItemsLayout": "barra di navigazione: layout del sottomenu",
        "group_extraMyset": "extraMyset",
        "group_font": "caratteri",
        "group_fontSize": "dimensioni dei caratteri",
        "group_formatBoolean": "formattazione booleana",
        "group_formatNumber": "formattazione dei numeri",
        "group_handySettings": "impostazioni del telefono cellulare",
        "group_icon": "icona",
        "group_iconListHeader": "Titolo",
        "group_icons": "icone",
        "group_iFrame": "Impostazioni iFrame",
        "group_image": "Immagine",
        "group_inputAppendix": "appendici dell'input",
        "group_inputLabel": "etichetta di input",
        "group_inputLayout": "input di layout",
        "group_inputSubText": "sottotesto di input",
        "group_label": "etichettatura",
        "group_labels": "etichette",
        "group_labelValuesAppend": "appendice testo valore",
        "group_layout": "disposizione",
        "group_layoutDialog": "Layout della finestra di dialogo",
        "group_layoutdialogCloseButton": "layout dei pulsanti del piè di pagina della finestra di dialogo",
        "group_layoutForData": "layout per i dati",
        "group_layoutTitle": "layout del titolo",
        "group_legendLayout": "layout legenda:",
        "group_lineLayout": "layout di linea",
        "group_lineValuesLayout": "layout dei valori del grafico a linee",
        "group_listData": "dati del menu",
        "group_listItemCardBackground": "sfondo di carta",
        "group_listItemData": "dati dell'elenco",
        "group_listItemLayout": "layout della voce di elenco",
        "group_listLayout": "layout dell'elenco",
        "group_lock": "Locking",
        "group_theme": "Tema",
        "group_menuColors": "colori dei menu",
        "group_menuItems": "elemento del menu",
        "group_oids": "dataset",
        "group_pieColors": "colori del grafico a torta:",
        "group_pieLayout": "layout grafico a torta:",
        "group_pieValuesLayout": "layout valori grafico a torta:",
        "group_rows": "layout della voce di elenco",
        "group_selectColor": "colori",
        "group_selectListLayout": "layout del menu",
        "group_submenus": "sottomenu",
        "group_tableLayout": "disposizione",
        "group_tabletSettings": "impostazioni del tablet",
        "group_thumbLabelLayout": "layout dell'etichetta del controller",
        "group_tickLayout": "passaggi layout",
        "group_tooltipLayout": "layout della descrizione comandi:",
        "group_topAppBarLayout": "layout della barra delle app principali",
        "group_valueTextColors": "valorizza i colori del testo",
        "group_View": "Visualizza",
        "group_viewsInColumn": "visualizzazioni in colonna",
        "group_xAxisLayout": "layout dell'asse x",
        "group_yAxisLayout": "layout dell'asse y",
        "group_yAxisLayoutForData": "layout dell'asse y per i dati"
    },
    "nl": {
        "group_alertLayout": "lay-out",
        "group_autoCompleteListLayout": "menu-indeling",
        "group_barColors": "staafdiagram kleuren:",
        "group_barLayout": "lay-out van staafdiagram:",
        "group_barValuesLayout": "lay-out waarden staafdiagram:",
        "group_buttonLayout": "Knopindeling",
        "group_buttonOids": "Object-id",
        "group_calendarButtonsLayout": "kalender knoppen lay-out",
        "group_calendarCustomFormats": "aangepaste datumnotaties",
        "group_calendarEventLayout": "afspraak lay-out",
        "group_calendarHeaderLayout": "kopindeling",
        "group_calendarLayout": "lay-out",
        "group_calendarTimeAxisLayout": "tijdasindeling",
        "group_calendarWeekNumbersLayout": "kalender weken lay-out",
        "group_changeEffect": "waarde verandering effect",
        "group_chartLayout": "grafiek layout:",
        "group_color": "kleuren",
        "group_columnLayout": "kolomindeling",
        "group_common": "Common",
        "group_title": "titel",
        "group_text": "tekst",
        "group_controlCard": "kaartactie",
        "group_formatLinked": "gekoppelde waarde",
        "group_layoutStriped": "gestreept",
        "group_listHeader": "lijstkop",
        "group_commonYAxis": "gemeenschappelijke y-as",
        "group_controlLayout": "besturingslay-out",
        "group_counter": "teller lay-out",
        "group_drawerColors": "kleuren van de navigatiebalk",
        "group_drawerDivider": "scheidingslijnen voor navigatiebalk",
        "group_drawerHeaders": "headers voor navigatiebalk",
        "group_drawerIcons": "pictogrammen voor navigatiebalk",
        "group_drawerItems": "item van navigatiebalk",
        "group_drawerItemsData": "gegevens van navigatiebalk",
        "group_drawerLabels": "label voor navigatiebalk",
        "group_drawerLayout": "navigatiebalk lay-out",
        "group_drawerSubItemsColors": "navigatiebalk: kleuren submenu",
        "group_drawerSubItemsLayout": "navigatiebalk: lay-out van het submenu",
        "group_extraMyset": "extraMyset",
        "group_font": "lettertypen",
        "group_fontSize": "lettergroottes",
        "group_formatBoolean": "booleaanse opmaak",
        "group_formatNumber": "nummeropmaak",
        "group_handySettings": "mobiele telefoon instellingen",
        "group_icon": "icoon",
        "group_iconListHeader": "kop",
        "group_icons": "pictogrammen",
        "group_iFrame": "iFrame-instellingen",
        "group_image": "beeld",
        "group_inputAppendix": "bijlagen van de invoer",
        "group_inputLabel": "label van invoer",
        "group_inputLayout": "layout invoer",
        "group_inputSubText": "subtekst van invoer",
        "group_label": "labeling",
        "group_labels": "labels",
        "group_labelValuesAppend": "waarde tekst bijlage",
        "group_layout": "indeling",
        "group_layoutDialog": "Dialoogvenster layout",
        "group_layoutdialogCloseButton": "lay-out van dialoogvoettekstknoppen",
        "group_layoutForData": "lay-out voor gegevens",
        "group_layoutTitle": "titel layout",
        "group_legendLayout": "legenda lay-out:",
        "group_lineLayout": "lijn layout",
        "group_lineValuesLayout": "indeling van lijngrafiekwaarden",
        "group_listData": "gegevens van menu",
        "group_listItemCardBackground": "kaart achtergrond",
        "group_listItemData": "gegevens van lijst",
        "group_listItemLayout": "lay-out van lijstitem",
        "group_listLayout": "indeling van de lijst",
        "group_lock": "Locking",
        "group_theme": "Thema",
        "group_menuColors": "menukleuren",
        "group_menuItems": "menu onderdeel",
        "group_oids": "dataset",
        "group_pieColors": "cirkeldiagram kleuren:",
        "group_pieLayout": "cirkeldiagramindeling:",
        "group_pieValuesLayout": "lay-out waarden cirkeldiagram:",
        "group_rows": "lay-out van lijstitem",
        "group_selectColor": "kleuren",
        "group_selectListLayout": "menu-indeling",
        "group_submenus": "submenu's",
        "group_tableLayout": "indeling",
        "group_tabletSettings": "tablet instellingen",
        "group_thumbLabelLayout": "lay-out van het controller-label",
        "group_tickLayout": "stappen lay-out",
        "group_tooltipLayout": "knopinfo lay-out:",
        "group_topAppBarLayout": "bovenste app-balkindeling",
        "group_valueTextColors": "waarde tekstkleuren",
        "group_View": "Visie",
        "group_viewsInColumn": "weergaven in kolom",
        "group_xAxisLayout": "x asindeling",
        "group_yAxisLayout": "y-aslay-out",
        "group_yAxisLayoutForData": "y-aslay-out voor gegevens"
    },
    "pl": {
        "group_alertLayout": "układ",
        "group_autoCompleteListLayout": "układ menu",
        "group_barColors": "kolory wykresu słupkowego:",
        "group_barLayout": "układ wykresu słupkowego:",
        "group_barValuesLayout": "układ wartości wykresu słupkowego:",
        "group_buttonLayout": "Układ przycisków",
        "group_buttonOids": "ID obiektu",
        "group_calendarButtonsLayout": "układ przycisków kalendarza",
        "group_calendarCustomFormats": "niestandardowe formaty dat",
        "group_calendarEventLayout": "układ spotkania",
        "group_calendarHeaderLayout": "układ nagłówka",
        "group_calendarLayout": "układ",
        "group_calendarTimeAxisLayout": "układ osi czasu",
        "group_calendarWeekNumbersLayout": "układ tygodni kalendarza",
        "group_changeEffect": "efekt zmiany wartości",
        "group_chartLayout": "układ wykresu:",
        "group_color": "zabarwienie",
        "group_columnLayout": "układ kolumn",
        "group_common": "Common",
        "group_title": "tytuł",
        "group_text": "tekst",
        "group_controlCard": "akcja karty",
        "group_formatLinked": "wartość powiązana",
        "group_layoutStriped": "paski",
        "group_listHeader": "nagłówek listy",
        "group_commonYAxis": "wspólna oś y",
        "group_controlLayout": "układ sterowania",
        "group_counter": "układ licznika",
        "group_drawerColors": "kolory paska nawigacyjnego",
        "group_drawerDivider": "przekładki do paska nawigacji",
        "group_drawerHeaders": "nagłówki paska nawigacji",
        "group_drawerIcons": "ikony paska nawigacji",
        "group_drawerItems": "element paska nawigacji",
        "group_drawerItemsData": "dane paska nawigacyjnego",
        "group_drawerLabels": "etykieta dla paska nawigacji",
        "group_drawerLayout": "układ paska nawigacyjnego",
        "group_drawerSubItemsColors": "pasek nawigacji: kolory podmenu",
        "group_drawerSubItemsLayout": "pasek nawigacji: układ podmenu",
        "group_extraMyset": "extraMyset",
        "group_font": "czcionki",
        "group_fontSize": "rozmiary czcionek",
        "group_formatBoolean": "formatowanie logiczne",
        "group_formatNumber": "formatowanie liczb",
        "group_handySettings": "ustawienia telefonu komórkowego",
        "group_icon": "Ikona",
        "group_iconListHeader": "Nagłówek",
        "group_icons": "ikony",
        "group_iFrame": "Ustawienia iFrame",
        "group_image": "wizerunek",
        "group_inputAppendix": "dodatki wejścia",
        "group_inputLabel": "etykieta wejściowa",
        "group_inputLayout": "układ wejściowy",
        "group_inputSubText": "podtekst wprowadzania",
        "group_label": "etykietowanie",
        "group_labels": "etykiety",
        "group_labelValuesAppend": "tekst wartości dodatku",
        "group_layout": "układ",
        "group_layoutDialog": "Układ okna dialogowego",
        "group_layoutdialogCloseButton": "układ przycisków stopki okna dialogowego",
        "group_layoutForData": "układ danych",
        "group_layoutTitle": "układ tytułu",
        "group_legendLayout": "układ legendy:",
        "group_lineLayout": "układ linii",
        "group_lineValuesLayout": "układ wartości wykresu liniowego",
        "group_listData": "dane menu",
        "group_listItemCardBackground": "tło karty",
        "group_listItemData": "dane listy",
        "group_listItemLayout": "układ elementu listy",
        "group_listLayout": "układ listy",
        "group_lock": "Zamykający",
        "group_theme": "Motyw",
        "group_menuColors": "kolory menu",
        "group_menuItems": "pozycja w menu",
        "group_oids": "zbiór danych",
        "group_pieColors": "kolory wykresu kołowego:",
        "group_pieLayout": "układ wykresu kołowego:",
        "group_pieValuesLayout": "układ wartości wykresu kołowego:",
        "group_rows": "układ elementu listy",
        "group_selectColor": "zabarwienie",
        "group_selectListLayout": "układ menu",
        "group_submenus": "podmenu",
        "group_tableLayout": "układ",
        "group_tabletSettings": "ustawienia tabletu",
        "group_thumbLabelLayout": "układ etykiety kontrolera",
        "group_tickLayout": "Układ kroków",
        "group_tooltipLayout": "układ podpowiedzi:",
        "group_topAppBarLayout": "górny układ paska aplikacji",
        "group_valueTextColors": "cenić kolory tekstu",
        "group_View": "Widok",
        "group_viewsInColumn": "widoki w kolumnie",
        "group_xAxisLayout": "układ osi x",
        "group_yAxisLayout": "układ osi y",
        "group_yAxisLayoutForData": "Układ osi y dla danych"
    },
    "pt": {
        "group_alertLayout": "disposição",
        "group_autoCompleteListLayout": "layout do menu",
        "group_barColors": "cores do gráfico de barras:",
        "group_barLayout": "layout do gráfico de barras:",
        "group_barValuesLayout": "layout dos valores do gráfico de barras:",
        "group_buttonLayout": "Layout do botão",
        "group_buttonOids": "Id do objeto",
        "group_calendarButtonsLayout": "layout de botões do calendário",
        "group_calendarCustomFormats": "formatos de data personalizados",
        "group_calendarEventLayout": "layout de compromisso",
        "group_calendarHeaderLayout": "layout do cabeçalho",
        "group_calendarLayout": "disposição",
        "group_calendarTimeAxisLayout": "layout do eixo do tempo",
        "group_calendarWeekNumbersLayout": "layout das semanas do calendário",
        "group_changeEffect": "efeito de mudança de valor",
        "group_chartLayout": "layout do gráfico:",
        "group_color": "cores",
        "group_columnLayout": "layout da coluna",
        "group_common": "Common",
        "group_title": "título",
        "group_text": "texto",
        "group_controlCard": "ação do cartão",
        "group_formatLinked": "valor vinculado",
        "group_layoutStriped": "listrado",
        "group_listHeader": "cabeçalho da lista",
        "group_commonYAxis": "eixo y comum",
        "group_controlLayout": "layout de controle",
        "group_counter": "layout do contador",
        "group_drawerColors": "cores da barra de navegação",
        "group_drawerDivider": "divisores para barra de navegação",
        "group_drawerHeaders": "cabeçalhos da barra de navegação",
        "group_drawerIcons": "ícones para barra de navegação",
        "group_drawerItems": "item da barra de navegação",
        "group_drawerItemsData": "dados da barra de navegação",
        "group_drawerLabels": "etiqueta para barra de navegação",
        "group_drawerLayout": "layout da barra de navegação",
        "group_drawerSubItemsColors": "barra de navegação: cores do submenu",
        "group_drawerSubItemsLayout": "barra de navegação: layout do submenu",
        "group_extraMyset": "extraMyset",
        "group_font": "fontes",
        "group_fontSize": "tamanhos de fonte",
        "group_formatBoolean": "formatação booleana",
        "group_formatNumber": "formatação de número",
        "group_handySettings": "configurações do telefone móvel",
        "group_icon": "ícone",
        "group_iconListHeader": "Título",
        "group_icons": "ícones",
        "group_iFrame": "configurações do iFrame",
        "group_image": "imagem",
        "group_inputAppendix": "apêndices da entrada",
        "group_inputLabel": "rótulo de entrada",
        "group_inputLayout": "entrada de layout",
        "group_inputSubText": "subtexto da entrada",
        "group_label": "marcação",
        "group_labels": "etiquetas",
        "group_labelValuesAppend": "apêndice de texto com valor",
        "group_layout": "disposição",
        "group_layoutDialog": "Layout da caixa de diálogo",
        "group_layoutdialogCloseButton": "layout dos botões de rodapé da caixa de diálogo",
        "group_layoutForData": "layout para dados",
        "group_layoutTitle": "layout do título",
        "group_legendLayout": "layout da legenda:",
        "group_lineLayout": "layout de linha",
        "group_lineValuesLayout": "layout dos valores do gráfico de linhas",
        "group_listData": "dados do menu",
        "group_listItemCardBackground": "fundo do cartão",
        "group_listItemData": "dados da lista",
        "group_listItemLayout": "layout do item da lista",
        "group_listLayout": "layout da lista",
        "group_lock": "Travamento",
        "group_theme": "Tema",
        "group_menuColors": "cores do menu",
        "group_menuItems": "item do menu",
        "group_oids": "conjunto de dados",
        "group_pieColors": "cores do gráfico de pizza:",
        "group_pieLayout": "layout do gráfico de pizza:",
        "group_pieValuesLayout": "layout dos valores do gráfico de setores circulares:",
        "group_rows": "layout do item da lista",
        "group_selectColor": "cores",
        "group_selectListLayout": "layout do menu",
        "group_submenus": "submenus",
        "group_tableLayout": "disposição",
        "group_tabletSettings": "configurações do tablet",
        "group_thumbLabelLayout": "layout da etiqueta do controlador",
        "group_tickLayout": "etapas Layout",
        "group_tooltipLayout": "layout da dica de ferramenta:",
        "group_topAppBarLayout": "layout da barra de aplicativos superior",
        "group_valueTextColors": "valor cores de texto",
        "group_View": "Visão",
        "group_viewsInColumn": "visualizações na coluna",
        "group_xAxisLayout": "layout do eixo x",
        "group_yAxisLayout": "layout do eixo y",
        "group_yAxisLayoutForData": "layout do eixo y para dados"
    },
    "ru": {
        "group_alertLayout": "расположение",
        "group_autoCompleteListLayout": "макет меню",
        "group_barColors": "цвета гистограммы:",
        "group_barLayout": "макет гистограммы:",
        "group_barValuesLayout": "макет значений гистограммы:",
        "group_buttonLayout": "Расположение кнопок",
        "group_buttonOids": "Идентификатор объекта",
        "group_calendarButtonsLayout": "расположение кнопок календаря",
        "group_calendarCustomFormats": "настраиваемые форматы даты",
        "group_calendarEventLayout": "макет назначения",
        "group_calendarHeaderLayout": "макет заголовка",
        "group_calendarLayout": "расположение",
        "group_calendarTimeAxisLayout": "расположение оси времени",
        "group_calendarWeekNumbersLayout": "макет календарных недель",
        "group_changeEffect": "эффект изменения стоимости",
        "group_chartLayout": "макет диаграммы:",
        "group_color": "цвета",
        "group_columnLayout": "расположение столбцов",
        "group_common": "Common",
        "group_title": "заголовок",
        "group_text": "текст",
        "group_controlCard": "действие карточки",
        "group_formatLinked": "связанное значение",
        "group_layoutStriped": "полосы",
        "group_listHeader": "заголовок списка",
        "group_commonYAxis": "общая ось Y",
        "group_controlLayout": "схема управления",
        "group_counter": "расположение счетчиков",
        "group_drawerColors": "цвета панели навигации",
        "group_drawerDivider": "разделители для панели навигации",
        "group_drawerHeaders": "заголовки для панели навигации",
        "group_drawerIcons": "иконки для панели навигации",
        "group_drawerItems": "элемент панели навигации",
        "group_drawerItemsData": "данные панели навигации",
        "group_drawerLabels": "ярлык для панели навигации",
        "group_drawerLayout": "расположение панели навигации",
        "group_drawerSubItemsColors": "панель навигации: цвета подменю",
        "group_drawerSubItemsLayout": "панель навигации: расположение подменю",
        "group_extraMyset": "extraMyset",
        "group_font": "шрифты",
        "group_fontSize": "размеры шрифта",
        "group_formatBoolean": "логическое форматирование",
        "group_formatNumber": "форматирование чисел",
        "group_handySettings": "настройки мобильного телефона",
        "group_icon": "икона",
        "group_iconListHeader": "Заголовок",
        "group_icons": "иконки",
        "group_iFrame": "Настройки iFrame",
        "group_image": "образ",
        "group_inputAppendix": "приложения ввода",
        "group_inputLabel": "метка ввода",
        "group_inputLayout": "ввод макета",
        "group_inputSubText": "подтекст ввода",
        "group_label": "Маркировка",
        "group_labels": "этикетки",
        "group_labelValuesAppend": "текстовое приложение значения",
        "group_layout": "расположение",
        "group_layoutDialog": "Макет диалога",
        "group_layoutdialogCloseButton": "макет кнопок нижнего колонтитула диалогового окна",
        "group_layoutForData": "макет для данных",
        "group_layoutTitle": "макет заголовка",
        "group_legendLayout": "макет легенды:",
        "group_lineLayout": "макет линии",
        "group_lineValuesLayout": "расположение значений линейного графика",
        "group_listData": "данные меню",
        "group_listItemCardBackground": "фон карты",
        "group_listItemData": "данные списка",
        "group_listItemLayout": "макет элемента списка",
        "group_listLayout": "макет списка",
        "group_lock": "запирающий",
        "group_theme": "Тема",
        "group_menuColors": "цвета меню",
        "group_menuItems": "пункт меню",
        "group_oids": "Набор данных",
        "group_pieColors": "Цвета круговой диаграммы:",
        "group_pieLayout": "макет круговой диаграммы:",
        "group_pieValuesLayout": "макет значений круговой диаграммы:",
        "group_rows": "макет элемента списка",
        "group_selectColor": "цвета",
        "group_selectListLayout": "макет меню",
        "group_submenus": "подменю",
        "group_tableLayout": "расположение",
        "group_tabletSettings": "настройки планшета",
        "group_thumbLabelLayout": "расположение метки контроллера",
        "group_tickLayout": "Расположение шагов",
        "group_tooltipLayout": "макет всплывающей подсказки:",
        "group_topAppBarLayout": "макет верхней панели приложения",
        "group_valueTextColors": "значение цвета текста",
        "group_View": "Посмотреть",
        "group_viewsInColumn": "просмотров в столбце",
        "group_xAxisLayout": "макет оси X",
        "group_yAxisLayout": "макет оси Y",
        "group_yAxisLayoutForData": "макет оси Y для данных"
    },
    "uk": {
        "group_alertLayout": "Макет",
        "group_autoCompleteListLayout": "Меню макет",
        "group_barColors": "Стовпчик діаграма COLORS:",
        "group_barLayout": "Стовпчик діаграма LAYOUT:",
        "group_barValuesLayout": "стовпчик діаграма значення макет:",
        "group_buttonLayout": "Кнопка макет",
        "group_buttonOids": "OBJECT ID",
        "group_calendarButtonsLayout": "CALENDAR кнопки макет",
        "group_calendarCustomFormats": "Власний дата FORMATS",
        "group_calendarEventLayout": "APPOINTMENT макет",
        "group_calendarHeaderLayout": "HEADING макет",
        "group_calendarLayout": "Макет",
        "group_calendarTimeAxisLayout": "Час вісь макет",
        "group_calendarWeekNumbersLayout": "CALENDAR WEEKS макет",
        "group_changeEffect": "Значення CHANGE EFFECT",
        "group_chartLayout": "Діаграма LAYOUT:",
        "group_color": "Кольори",
        "group_columnLayout": "Стовпець макет",
        "group_common": "Common",
        "group_title": "заголовок",
        "group_text": "текст",
        "group_controlCard": "дія картки",
        "group_formatLinked": "пов'язане значення",
        "group_layoutStriped": "смуги",
        "group_listHeader": "заголовок списку",
        "group_commonYAxis": "COMMON Y вісь",
        "group_controlLayout": "Керування макет",
        "group_counter": "COUNTER макет",
        "group_drawerColors": "Навігація стовпчик кольори",
        "group_drawerDivider": "розділювачі for навігація стовпчик",
        "group_drawerHeaders": "headers for навігація стовпчик",
        "group_drawerIcons": "іконки for навігація стовпчик",
        "group_drawerItems": "ITEM OF навігація стовпчик",
        "group_drawerItemsData": "Дані OF навігація стовпчик",
        "group_drawerLabels": "мітка for навігація стовпчик",
        "group_drawerLayout": "Навігація стовпчик макет",
        "group_drawerSubItemsColors": "навігація стовпчик: sub меню кольори",
        "group_drawerSubItemsLayout": "навігація стовпчик: sub меню макет",
        "group_extraMyset": "EXTRA MYSET",
        "group_font": "Шрифти",
        "group_fontSize": "Шрифт SIZES",
        "group_formatBoolean": "BOOLEAN FORMATTING",
        "group_formatNumber": "Число FORMATTING",
        "group_handySettings": "MOBILE PHONE SETTINGS",
        "group_icon": "Іконка",
        "group_iconListHeader": "HEADLINE",
        "group_icons": "Іконки",
        "group_iFrame": "I рамка SETTINGS",
        "group_image": "Зображення",
        "group_inputAppendix": "APPENDIXS OF THE ввід",
        "group_inputLabel": "Мітка OF ввід",
        "group_inputLayout": "Макет ввід",
        "group_inputSubText": "SUB текст OF ввід",
        "group_label": "LABELING",
        "group_labels": "LABELS",
        "group_labelValuesAppend": "Значення текст APPENDIX",
        "group_layout": "Макет",
        "group_layoutDialog": "Діалог макет",
        "group_layoutdialogCloseButton": "макет of діалог нижній колонтитул кнопки",
        "group_layoutForData": "Макет FOR дані",
        "group_layoutTitle": "Заголовок макет",
        "group_legendLayout": "Легенда LAYOUT:",
        "group_lineLayout": "Лінія макет",
        "group_lineValuesLayout": "макет of лінія діаграма значення",
        "group_listData": "Дані OF меню",
        "group_listItemCardBackground": "Картка фон",
        "group_listItemData": "Дані OF список",
        "group_listItemLayout": "Макет OF список ITEM",
        "group_listLayout": "Макет OF список",
        "group_lock": "LOCKING",
        "group_theme": "Тема",
        "group_menuColors": "Меню кольори",
        "group_menuItems": "Меню ITEM",
        "group_oids": "DATASET",
        "group_pieColors": "Кругова діаграма COLORS:",
        "group_pieLayout": "Кругова діаграма LAYOUT:",
        "group_pieValuesLayout": "кругова діаграма значення макет:",
        "group_rows": "Макет OF список ITEM",
        "group_selectColor": "Кольори",
        "group_selectListLayout": "Меню макет",
        "group_submenus": "SUB MENUS",
        "group_tableLayout": "Макет",
        "group_tabletSettings": "TABLET SETTINGS",
        "group_thumbLabelLayout": "макет of the controller мітка",
        "group_tickLayout": "STEPS макет",
        "group_tooltipLayout": "Підказка LAYOUT:",
        "group_topAppBarLayout": "Верх APP стовпчик макет",
        "group_valueTextColors": "Значення текст кольори",
        "group_View": "Вигляд",
        "group_viewsInColumn": "Вигляди IN стовпець",
        "group_xAxisLayout": "X вісь макет",
        "group_yAxisLayout": "Y вісь макет",
        "group_yAxisLayoutForData": "Y вісь макет FOR дані"
    },
    "zh-cn": {
        "group_alertLayout": "布局",
        "group_autoCompleteListLayout": "菜单布局",
        "group_barColors": "条形图颜色：",
        "group_barLayout": "条形图布局：",
        "group_barValuesLayout": "条形图值布局：",
        "group_buttonLayout": "按钮布局",
        "group_buttonOids": "对象编号",
        "group_calendarButtonsLayout": "日历按钮布局",
        "group_calendarCustomFormats": "自定义日期格式",
        "group_calendarEventLayout": "约会安排",
        "group_calendarHeaderLayout": "标题布局",
        "group_calendarLayout": "布局",
        "group_calendarTimeAxisLayout": "时间轴布局",
        "group_calendarWeekNumbersLayout": "日历周布局",
        "group_changeEffect": "价值变化效应",
        "group_chartLayout": "图表布局：",
        "group_color": "颜色",
        "group_columnLayout": "列布局",
        "group_common": "Common",
        "group_title": "标题",
        "group_text": "文本",
        "group_controlCard": "卡片操作",
        "group_formatLinked": "关联值",
        "group_layoutStriped": "条纹",
        "group_listHeader": "列表标题",
        "group_commonYAxis": "共同y轴",
        "group_controlLayout": "控制布局",
        "group_counter": "柜台布局",
        "group_drawerColors": "导航栏颜色",
        "group_drawerDivider": "导航栏分隔线",
        "group_drawerHeaders": "导航栏标题",
        "group_drawerIcons": "导航栏图标",
        "group_drawerItems": "导航栏项目",
        "group_drawerItemsData": "导航栏数据",
        "group_drawerLabels": "导航栏标签",
        "group_drawerLayout": "导航栏布局",
        "group_drawerSubItemsColors": "导航栏：子菜单颜色",
        "group_drawerSubItemsLayout": "导航栏：子菜单布局",
        "group_extraMyset": "extraMyset",
        "group_font": "字型",
        "group_fontSize": "字体大小",
        "group_formatBoolean": "布尔格式",
        "group_formatNumber": "数字格式",
        "group_handySettings": "手机设定",
        "group_icon": "图标",
        "group_iconListHeader": "标题",
        "group_icons": "图标",
        "group_iFrame": "iFrame设置",
        "group_image": "图片",
        "group_inputAppendix": "输入的附录",
        "group_inputLabel": "输入标签",
        "group_inputLayout": "布局输入",
        "group_inputSubText": "输入的子文字",
        "group_label": "标签",
        "group_labels": "标签",
        "group_labelValuesAppend": "值文本附录",
        "group_layout": "布局",
        "group_layoutDialog": "对话框布局",
        "group_layoutdialogCloseButton": "对话框页脚按钮的布局",
        "group_layoutForData": "数据布局",
        "group_layoutTitle": "标题布局",
        "group_legendLayout": "图例布局：",
        "group_lineLayout": "线布局",
        "group_lineValuesLayout": "折线图值的布局",
        "group_listData": "菜单数据",
        "group_listItemCardBackground": "卡背景",
        "group_listItemData": "清单数据",
        "group_listItemLayout": "清单项目的布局",
        "group_listLayout": "列表的布局",
        "group_lock": "锁定",
        "group_theme": "主题",
        "group_menuColors": "菜单颜色",
        "group_menuItems": "菜单项",
        "group_oids": "资料集",
        "group_pieColors": "饼图颜色：",
        "group_pieLayout": "饼图布局：",
        "group_pieValuesLayout": "饼图值布局：",
        "group_rows": "清单项目的布局",
        "group_selectColor": "颜色",
        "group_selectListLayout": "菜单布局",
        "group_submenus": "子菜单",
        "group_tableLayout": "布局",
        "group_tabletSettings": "平板电脑设置",
        "group_thumbLabelLayout": "控制器标签的布局",
        "group_tickLayout": "步骤布局",
        "group_tooltipLayout": "工具提示布局：",
        "group_topAppBarLayout": "顶部应用栏布局",
        "group_valueTextColors": "值文字颜色",
        "group_View": "视图",
        "group_viewsInColumn": "列中的视图",
        "group_xAxisLayout": "x轴布局",
        "group_yAxisLayout": "y轴布局",
        "group_yAxisLayoutForData": "数据的Y轴布局"
    }
}
